virtualenv_tools.py
virtualenv_tools4-3.1.2.dist-info/LICENSE
virtualenv_tools4-3.1.2.dist-info/METADATA
virtualenv_tools4-3.1.2.dist-info/WHEEL
virtualenv_tools4-3.1.2.dist-info/entry_points.txt
virtualenv_tools4-3.1.2.dist-info/top_level.txt
virtualenv_tools4-3.1.2.dist-info/RECORD
