Metadata-Version: 2.2
Name: virtualenv_tools4
Version: 3.1.2
Summary: A set of tools for virtualenv
Home-page: http://github.com/Yelp/virtualenv-tools
Author: Fireteam Ltd.; Yelp, Inc ; Devopsy.
Author-email: gaspard@devopsy.fr
Classifier: License :: OSI Approved :: BSD License
Classifier: Programming Language :: Python
Classifier: Programming Language :: Python :: 3
Classifier: Programming Language :: Python :: 3 :: Only
Classifier: Programming Language :: Python :: Implementation :: CPython
Classifier: Programming Language :: Python :: Implementation :: PyPy
Requires-Python: >=3.8
License-File: LICENSE
